{
  "id": "meteorite40_low",
  "name": "meteorite40_low",
  "keyboard_name": "meteorite40_low",
  "url": "https://github.com/iwk7273/zmk-config-meteorite40",
  "layouts": {
    "low_profile_default": {
      "layout": [
        { "x":    0, "y": 0, "row": 0, "col":  0 },
        { "x":    1, "y": 0, "row": 0, "col":  1 },
        { "x":    2, "y": 0, "row": 0, "col":  2 },
        { "x":    3, "y": 0, "row": 0, "col":  3 },
        { "x":    4, "y": 0, "row": 0, "col":  4 },
        { "x":    7, "y": 0, "row": 0, "col":  5 },
        { "x":    8, "y": 0, "row": 0, "col":  6 },
        { "x":    9, "y": 0, "row": 0, "col":  7 },
        { "x":   10, "y": 0, "row": 0, "col":  8 },
        { "x":   11, "y": 0, "row": 0, "col":  9 },

        { "x":    0, "y": 1, "row": 1, "col":  0 },
        { "x":    1, "y": 1, "row": 1, "col":  1 },
        { "x":    2, "y": 1, "row": 1, "col":  2 },
        { "x":    3, "y": 1, "row": 1, "col":  3 },
        { "x":    4, "y": 1, "row": 1, "col":  4 },
        { "x":    7, "y": 1, "row": 1, "col":  5 },
        { "x":    8, "y": 1, "row": 1, "col":  6 },
        { "x":    9, "y": 1, "row": 1, "col":  7 },
        { "x":   10, "y": 1, "row": 1, "col":  8 },
        { "x":   11, "y": 1, "row": 1, "col":  9 },

        { "x":    0, "y": 2, "row": 2, "col":  0 },
        { "x":    1, "y": 2, "row": 2, "col":  1 },
        { "x":    2, "y": 2, "row": 2, "col":  2 },
        { "x":    3, "y": 2, "row": 2, "col":  3 },
        { "x":    4, "y": 2, "row": 2, "col":  4 },
        { "x":    5, "y": 2, "row": 2, "col":  5 },
        { "x":    6, "y": 2, "row": 2, "col":  6 },
        { "x":    7, "y": 2, "row": 2, "col":  7 },
        { "x":    8, "y": 2, "row": 2, "col":  8 },
        { "x":    9, "y": 2, "row": 2, "col":  9 },
        { "x":   10, "y": 2, "row": 2, "col": 10 },
        { "x":   11, "y": 2, "row": 2, "col": 11 },

        { "x": 1.25, "y": 3, "row": 3, "col":  0 },
        { "x": 2.25, "y": 3, "row": 3, "col":  1 },
        { "x": 3.25, "y": 3, "row": 3, "col":  2, "w":  1.5 },
        { "x": 4.75, "y": 3, "row": 3, "col":  3, "w": 1.25 },
        { "x":    6, "y": 3, "row": 3, "col":  4, "w": 1.75 },
        { "x": 7.75, "y": 3, "row": 3, "col":  5 },
        { "x": 8.75, "y": 3, "row": 3, "col":  6 },
        { "x": 9.75, "y": 3, "row": 3, "col":  7 }
      ]
    }
  },
  "sensors": []
}